{
  "spreadsheet_id": "1vTbs9INOf60aKsA_wVmp8SxbFnOGrKroKKJu7uazaLTWHeM8C01tPbviJVci2uegA1qNJFW8wcu5YfX",
  "worksheet_name": "Yelp Restaurants - New York, NY",
  "timestamp": "2025-09-09 16:29:51",
  "total_rows": 20,
  "data": [
    {
      "Business Name": "Bella Vista New York",
      "Phone": "(626) 660-4405",
      "Email": "info@bellavista.com",
      "Address": "245 Main Street, New York, NY",
      "Website": "https://bellavista.com",
      "Category": "Italian Restaurant",
      "Rating": 4.4,
      "Reviews": 159,
      "Price Range": "$$$",
      "Neighborhood": "Downtown",
      "Hours": "Mon-Sun: 9AM-9PM",
      "Description": "Authentic Italian cuisine",
      "Yelp URL": "https://yelp.com/biz/bella-vista-restaurant",
      "Scraped Date": "2025-09-09 16:29:51",
      "Search Query": "restaurants",
      "Search Location": "New York, NY"
    },
    {
      "Business Name": "Bella Vista New York",
      "Phone": "(800) 864-7330",
      "Email": "info@bellavista.com",
      "Address": "245 Main Street, New York, NY",
      "Website": "https://bellavista.com",
      "Category": "Italian Restaurant",
      "Rating": 4.7,
      "Reviews": 790,
      "Price Range": "$$",
      "Neighborhood": "Downtown",
      "Hours": "Mon-Sun: 9AM-9PM",
      "Description": "Authentic Italian cuisine",
      "Yelp URL": "https://yelp.com/biz/bella-vista-restaurant",
      "Scraped Date": "2025-09-09 16:29:51",
      "Search Query": "restaurants",
      "Search Location": "New York, NY"
    },
    {
      "Business Name": "Bella Vista New York",
      "Phone": "(247) 293-6579",
      "Email": "info@bellavista.com",
      "Address": "245 Main Street, New York, NY",
      "Website": "https://bellavista.com",
      "Category": "Italian Restaurant",
      "Rating": 3.7,
      "Reviews": 680,
      "Price Range": "$$$",
      "Neighborhood": "Downtown",
      "Hours": "Mon-Sun: 9AM-9PM",
      "Description": "Authentic Italian cuisine",
      "Yelp URL": "https://yelp.com/biz/bella-vista-restaurant",
      "Scraped Date": "2025-09-09 16:29:51",
      "Search Query": "restaurants",
      "Search Location": "New York, NY"
    },
    {
      "Business Name": "Bella Vista New York",
      "Phone": "(839) 695-8523",
      "Email": "info@bellavista.com",
      "Address": "245 Main Street, New York, NY",
      "Website": "https://bellavista.com",
      "Category": "Italian Restaurant",
      "Rating": 3.7,
      "Reviews": 211,
      "Price Range": "$$$",
      "Neighborhood": "Downtown",
      "Hours": "Mon-Sun: 9AM-9PM",
      "Description": "Authentic Italian cuisine",
      "Yelp URL": "https://yelp.com/biz/bella-vista-restaurant",
      "Scraped Date": "2025-09-09 16:29:51",
      "Search Query": "restaurants",
      "Search Location": "New York, NY"
    },
    {
      "Business Name": "Bella Vista New York",
      "Phone": "(972) 403-5411",
      "Email": "info@bellavista.com",
      "Address": "245 Main Street, New York, NY",
      "Website": "https://bellavista.com",
      "Category": "Italian Restaurant",
      "Rating": 4.2,
      "Reviews": 777,
      "Price Range": "$",
      "Neighborhood": "Downtown",
      "Hours": "Mon-Sun: 9AM-9PM",
      "Description": "Authentic Italian cuisine",
      "Yelp URL": "https://yelp.com/biz/bella-vista-restaurant",
      "Scraped Date": "2025-09-09 16:29:51",
      "Search Query": "restaurants",
      "Search Location": "New York, NY"
    },
    {
      "Business Name": "Bella Vista New York",
      "Phone": "(717) 463-2255",
      "Email": "info@bellavista.com",
      "Address": "245 Main Street, New York, NY",
      "Website": "https://bellavista.com",
      "Category": "Italian Restaurant",
      "Rating": 4.7,
      "Reviews": 206,
      "Price Range": "$$",
      "Neighborhood": "Downtown",
      "Hours": "Mon-Sun: 9AM-9PM",
      "Description": "Authentic Italian cuisine",
      "Yelp URL": "https://yelp.com/biz/bella-vista-restaurant",
      "Scraped Date": "2025-09-09 16:29:51",
      "Search Query": "restaurants",
      "Search Location": "New York, NY"
    },
    {
      "Business Name": "Sakura Sushi New York",
      "Phone": "(417) 307-8275",
      "Email": "orders@sakurasushi.com",
      "Address": "123 Pine Street, New York, NY",
      "Website": "https://sakurasushi.com",
      "Category": "Japanese Restaurant",
      "Rating": 5.0,
      "Reviews": 465,
      "Price Range": "$$$",
      "Neighborhood": "Downtown",
      "Hours": "Mon-Sun: 9AM-9PM",
      "Description": "Fresh sushi and Japanese cuisine",
      "Yelp URL": "https://yelp.com/biz/sakura-sushi",
      "Scraped Date": "2025-09-09 16:29:51",
      "Search Query": "restaurants",
      "Search Location": "New York, NY"
    },
    {
      "Business Name": "Bella Vista New York",
      "Phone": "(901) 294-2199",
      "Email": "info@bellavista.com",
      "Address": "245 Main Street, New York, NY",
      "Website": "https://bellavista.com",
      "Category": "Italian Restaurant",
      "Rating": 4.4,
      "Reviews": 682,
      "Price Range": "$$",
      "Neighborhood": "Downtown",
      "Hours": "Mon-Sun: 9AM-9PM",
      "Description": "Authentic Italian cuisine",
      "Yelp URL": "https://yelp.com/biz/bella-vista-restaurant",
      "Scraped Date": "2025-09-09 16:29:51",
      "Search Query": "restaurants",
      "Search Location": "New York, NY"
    },
    {
      "Business Name": "Bella Vista New York",
      "Phone": "(882) 595-1502",
      "Email": "info@bellavista.com",
      "Address": "245 Main Street, New York, NY",
      "Website": "https://bellavista.com",
      "Category": "Italian Restaurant",
      "Rating": 4.1,
      "Reviews": 64,
      "Price Range": "$",
      "Neighborhood": "Downtown",
      "Hours": "Mon-Sun: 9AM-9PM",
      "Description": "Authentic Italian cuisine",
      "Yelp URL": "https://yelp.com/biz/bella-vista-restaurant",
      "Scraped Date": "2025-09-09 16:29:51",
      "Search Query": "restaurants",
      "Search Location": "New York, NY"
    },
    {
      "Business Name": "The Local Burger - New York",
      "Phone": "(424) 446-8184",
      "Email": "hello@localburger.com",
      "Address": "678 Oak Avenue, New York, NY",
      "Website": "https://localburger.com",
      "Category": "American Restaurant",
      "Rating": 4.3,
      "Reviews": 157,
      "Price Range": "$",
      "Neighborhood": "Downtown",
      "Hours": "Mon-Sun: 9AM-9PM",
      "Description": "Fresh, locally sourced burgers",
      "Yelp URL": "https://yelp.com/biz/local-burger",
      "Scraped Date": "2025-09-09 16:29:51",
      "Search Query": "restaurants",
      "Search Location": "New York, NY"
    },
    {
      "Business Name": "Sakura Sushi New York",
      "Phone": "(817) 335-1014",
      "Email": "orders@sakurasushi.com",
      "Address": "123 Pine Street, New York, NY",
      "Website": "https://sakurasushi.com",
      "Category": "Japanese Restaurant",
      "Rating": 4.7,
      "Reviews": 194,
      "Price Range": "$",
      "Neighborhood": "Downtown",
      "Hours": "Mon-Sun: 9AM-9PM",
      "Description": "Fresh sushi and Japanese cuisine",
      "Yelp URL": "https://yelp.com/biz/sakura-sushi",
      "Scraped Date": "2025-09-09 16:29:51",
      "Search Query": "restaurants",
      "Search Location": "New York, NY"
    },
    {
      "Business Name": "The Local Burger - New York",
      "Phone": "(679) 674-9274",
      "Email": "hello@localburger.com",
      "Address": "678 Oak Avenue, New York, NY",
      "Website": "https://localburger.com",
      "Category": "American Restaurant",
      "Rating": 4.8,
      "Reviews": 770,
      "Price Range": "$$",
      "Neighborhood": "Downtown",
      "Hours": "Mon-Sun: 9AM-9PM",
      "Description": "Fresh, locally sourced burgers",
      "Yelp URL": "https://yelp.com/biz/local-burger",
      "Scraped Date": "2025-09-09 16:29:51",
      "Search Query": "restaurants",
      "Search Location": "New York, NY"
    },
    {
      "Business Name": "The Local Burger - New York",
      "Phone": "(895) 377-5703",
      "Email": "hello@localburger.com",
      "Address": "678 Oak Avenue, New York, NY",
      "Website": "https://localburger.com",
      "Category": "American Restaurant",
      "Rating": 4.2,
      "Reviews": 116,
      "Price Range": "$",
      "Neighborhood": "Downtown",
      "Hours": "Mon-Sun: 9AM-9PM",
      "Description": "Fresh, locally sourced burgers",
      "Yelp URL": "https://yelp.com/biz/local-burger",
      "Scraped Date": "2025-09-09 16:29:51",
      "Search Query": "restaurants",
      "Search Location": "New York, NY"
    },
    {
      "Business Name": "The Local Burger - New York",
      "Phone": "(879) 554-2310",
      "Email": "hello@localburger.com",
      "Address": "678 Oak Avenue, New York, NY",
      "Website": "https://localburger.com",
      "Category": "American Restaurant",
      "Rating": 4.1,
      "Reviews": 702,
      "Price Range": "$$$",
      "Neighborhood": "Downtown",
      "Hours": "Mon-Sun: 9AM-9PM",
      "Description": "Fresh, locally sourced burgers",
      "Yelp URL": "https://yelp.com/biz/local-burger",
      "Scraped Date": "2025-09-09 16:29:51",
      "Search Query": "restaurants",
      "Search Location": "New York, NY"
    },
    {
      "Business Name": "Sakura Sushi New York",
      "Phone": "(342) 522-8992",
      "Email": "orders@sakurasushi.com",
      "Address": "123 Pine Street, New York, NY",
      "Website": "https://sakurasushi.com",
      "Category": "Japanese Restaurant",
      "Rating": 3.6,
      "Reviews": 547,
      "Price Range": "$$$",
      "Neighborhood": "Downtown",
      "Hours": "Mon-Sun: 9AM-9PM",
      "Description": "Fresh sushi and Japanese cuisine",
      "Yelp URL": "https://yelp.com/biz/sakura-sushi",
      "Scraped Date": "2025-09-09 16:29:51",
      "Search Query": "restaurants",
      "Search Location": "New York, NY"
    },
    {
      "Business Name": "Sakura Sushi New York",
      "Phone": "(823) 601-9069",
      "Email": "orders@sakurasushi.com",
      "Address": "123 Pine Street, New York, NY",
      "Website": "https://sakurasushi.com",
      "Category": "Japanese Restaurant",
      "Rating": 4.7,
      "Reviews": 587,
      "Price Range": "$",
      "Neighborhood": "Downtown",
      "Hours": "Mon-Sun: 9AM-9PM",
      "Description": "Fresh sushi and Japanese cuisine",
      "Yelp URL": "https://yelp.com/biz/sakura-sushi",
      "Scraped Date": "2025-09-09 16:29:51",
      "Search Query": "restaurants",
      "Search Location": "New York, NY"
    },
    {
      "Business Name": "Bella Vista New York",
      "Phone": "(689) 281-2643",
      "Email": "info@bellavista.com",
      "Address": "245 Main Street, New York, NY",
      "Website": "https://bellavista.com",
      "Category": "Italian Restaurant",
      "Rating": 4.6,
      "Reviews": 339,
      "Price Range": "$",
      "Neighborhood": "Downtown",
      "Hours": "Mon-Sun: 9AM-9PM",
      "Description": "Authentic Italian cuisine",
      "Yelp URL": "https://yelp.com/biz/bella-vista-restaurant",
      "Scraped Date": "2025-09-09 16:29:51",
      "Search Query": "restaurants",
      "Search Location": "New York, NY"
    },
    {
      "Business Name": "Sakura Sushi New York",
      "Phone": "(483) 548-9935",
      "Email": "orders@sakurasushi.com",
      "Address": "123 Pine Street, New York, NY",
      "Website": "https://sakurasushi.com",
      "Category": "Japanese Restaurant",
      "Rating": 4.8,
      "Reviews": 656,
      "Price Range": "$$",
      "Neighborhood": "Downtown",
      "Hours": "Mon-Sun: 9AM-9PM",
      "Description": "Fresh sushi and Japanese cuisine",
      "Yelp URL": "https://yelp.com/biz/sakura-sushi",
      "Scraped Date": "2025-09-09 16:29:51",
      "Search Query": "restaurants",
      "Search Location": "New York, NY"
    },
    {
      "Business Name": "Sakura Sushi New York",
      "Phone": "(747) 690-3485",
      "Email": "orders@sakurasushi.com",
      "Address": "123 Pine Street, New York, NY",
      "Website": "https://sakurasushi.com",
      "Category": "Japanese Restaurant",
      "Rating": 4.1,
      "Reviews": 416,
      "Price Range": "$",
      "Neighborhood": "Downtown",
      "Hours": "Mon-Sun: 9AM-9PM",
      "Description": "Fresh sushi and Japanese cuisine",
      "Yelp URL": "https://yelp.com/biz/sakura-sushi",
      "Scraped Date": "2025-09-09 16:29:51",
      "Search Query": "restaurants",
      "Search Location": "New York, NY"
    },
    {
      "Business Name": "The Local Burger - New York",
      "Phone": "(464) 308-4702",
      "Email": "hello@localburger.com",
      "Address": "678 Oak Avenue, New York, NY",
      "Website": "https://localburger.com",
      "Category": "American Restaurant",
      "Rating": 3.9,
      "Reviews": 38,
      "Price Range": "$",
      "Neighborhood": "Downtown",
      "Hours": "Mon-Sun: 9AM-9PM",
      "Description": "Fresh, locally sourced burgers",
      "Yelp URL": "https://yelp.com/biz/local-burger",
      "Scraped Date": "2025-09-09 16:29:51",
      "Search Query": "restaurants",
      "Search Location": "New York, NY"
    }
  ]
}